{
    "planningLength": 91,
    "sprayingPopEff": 0.85,
    "freshYield": 0.8623,
    "juiceYield": 0.0,
    "freshPrice": 17.60,
    "juicePrice": 0.0,
    "costs": 11718.47,
    "biologicalRun": false,
    "numIndividualSprays": 3,
    "numGroupSprays": 6,
    "projectionLength": 1825,
    "sprayCost": 67.73,
    "groupWindow": 21,
    "individualWindow": 60,
    "g00_lambda": 0,
    "g01_lambda": 0,
    "g02_lambda": 0,
    "g10_lambda": 0,
    "g11_lambda": 0,
    "g12_lambda": 0,
    "g20_lambda": 0,
    "g21_lambda": 0,
    "g22_lambda": 0,
    "g00_alpha": 1,
    "g01_alpha": 1,
    "g02_alpha": 1,
    "g10_alpha": 1,
    "g11_alpha": 1,
    "g12_alpha": 1,
    "g20_alpha": 1,
    "g21_alpha": 1,
    "g22_alpha": 1,    
    "g00_behavior": 0,
    "g01_behavior": 0,
    "g02_behavior": 0,
    "g10_behavior": 0,
    "g11_behavior": 0,
    "g12_behavior": 0,
    "g20_behavior": 0,
    "g21_behavior": 0,
    "g22_behavior": 0,
    "g00_agency": true,
    "g01_agency": true,
    "g02_agency": true,
    "g10_agency": true,
    "g11_agency": true,
    "g12_agency": true,
    "g20_agency": true,
    "g21_agency": true,
    "g22_agency": true,
    "g00_premium": 0,
    "g01_premium": 0,
    "g02_premium": 0,
    "g10_premium": 0,
    "g11_premium": 0,
    "g12_premium": 0,
    "g20_premium": 0,
    "g21_premium": 0,
    "g22_premium": 0,
    "harvestFilename": "configs/commodity/harvest.txt",
    "baselineFilename": "configs/survival/baseline.txt",
    "timeBucketsFilename": "configs/survival/timebuckets.txt",
    "rowPsyllidsWeight": -0.3229028688,
    "colPsyllidsWeight": -1.1126303662,
    "rowPsyllidsMean": 28871.0220470756,
    "colPsyllidsMean": 42297.6759313727, 
    "rowPsyllidsScale": 31724.0168350790,
    "colPsyllidsScale": 36256.7422442492,
    "outputFilename": "econ_output.csv",
    "experimentID": -1
}